pxrun-0.1.1.dist-info/licenses/LICENSE
src/__init__.py
src/exceptions.py
src/cli/__init__.py
src/cli/__main__.py
src/cli/prompts.py
src/cli/commands/__init__.py
src/cli/commands/create.py
src/cli/commands/destroy.py
src/cli/commands/list.py
src/cli/commands/save_config.py
src/cli/commands/setup.py
src/cli/commands/tailscale.py
src/lib/__init__.py
src/models/__init__.py
src/models/cluster.py
src/models/container.py
src/models/mount.py
src/models/provisioning.py
src/models/storage.py
src/models/tailscale.py
src/models/template.py
src/models/user.py
src/proxmox/__init__.py
src/proxmox/api.py
src/proxmox/auth.py
src/proxmox/client.py
src/services/__init__.py
src/services/config_manager.py
src/services/credentials.py
src/services/node_selector.py
src/services/proxmox.py
src/services/ssh_provisioner.py
src/services/tailscale.py
src/utils/__init__.py
src/utils/output_manager.py
pxrun-0.1.1.dist-info/METADATA
pxrun-0.1.1.dist-info/WHEEL
pxrun-0.1.1.dist-info/entry_points.txt
pxrun-0.1.1.dist-info/top_level.txt
pxrun-0.1.1.dist-info/RECORD
