Metadata-Version: 2.4
Name: pxrun
Version: 0.1.1
Summary: Proxmox LXC Lifecycle Management Tool
Home-page: https://github.com/yourusername/pxrun
Author: Your Name
Author-email: Your Name <your.email@example.com>
License: MIT
Project-URL: Homepage, https://github.com/yourusername/pxrun
Project-URL: Documentation, https://github.com/yourusername/pxrun/blob/main/README.md
Project-URL: Repository, https://github.com/yourusername/pxrun.git
Project-URL: Bug Tracker, https://github.com/yourusername/pxrun/issues
Project-URL: Changelog, https://github.com/yourusername/pxrun/blob/main/CHANGELOG.md
Keywords: proxmox,lxc,containers,virtualization,cli
Classifier: Development Status :: 3 - Alpha
Classifier: Intended Audience :: Developers
Classifier: Topic :: System :: Systems Administration
Classifier: License :: OSI Approved :: MIT License
Classifier: Programming Language :: Python :: 3
Classifier: Programming Language :: Python :: 3.11
Classifier: Programming Language :: Python :: 3.12
Requires-Python: >=3.9
License-File: LICENSE
Requires-Dist: proxmoxer>=2.0.1
Requires-Dist: paramiko>=3.3.1
Requires-Dist: PyYAML>=6.0.1
Requires-Dist: click>=8.1.7
Requires-Dist: python-dotenv>=1.0.0
Requires-Dist: cryptography>=41.0.7
Requires-Dist: requests>=2.31.0
Requires-Dist: tabulate>=0.9.0
Requires-Dist: colorama>=0.4.6
Requires-Dist: rich>=13.7.0
Provides-Extra: dev
Requires-Dist: pytest>=7.4.3; extra == "dev"
Requires-Dist: pytest-mock>=3.12.0; extra == "dev"
Requires-Dist: pytest-cov>=4.1.0; extra == "dev"
Requires-Dist: pytest-asyncio>=0.21.1; extra == "dev"
Requires-Dist: responses>=0.24.1; extra == "dev"
Requires-Dist: jsonschema>=4.19.2; extra == "dev"
Requires-Dist: black>=23.12.0; extra == "dev"
Requires-Dist: ruff>=0.1.9; extra == "dev"
Requires-Dist: mypy>=1.7.1; extra == "dev"
Requires-Dist: types-requests>=2.31.0.10; extra == "dev"
Requires-Dist: types-paramiko>=3.3.0.0; extra == "dev"
Requires-Dist: types-PyYAML>=6.0.12.12; extra == "dev"
Requires-Dist: types-tabulate>=0.9.0.3; extra == "dev"
Requires-Dist: sphinx>=7.2.6; extra == "dev"
Requires-Dist: sphinx-rtd-theme>=2.0.0; extra == "dev"
Requires-Dist: sphinx-click>=5.1.0; extra == "dev"
Requires-Dist: ipython>=8.18.1; extra == "dev"
Requires-Dist: ipdb>=0.13.13; extra == "dev"
Requires-Dist: pre-commit>=3.6.0; extra == "dev"
Dynamic: author
Dynamic: home-page
Dynamic: license-file
Dynamic: requires-python
